{
  "target_rows": 50000,
  "fallback_ratio": 0.38,
  "languages": [
    "ru"
  ],
  "punctuation": [
    "",
    "?",
    ".",
    "!"
  ],
  "case_variants": [
    "as_is",
    "capitalize",
    "lower",
    "upper"
  ],
  "available_tools_per_row": [
    7,
    12
  ],
  "decoy_tools_per_row": 3,
  "decoy_tools": [
    {
      "name": "open_browser",
      "tags": [
        "браузер",
        "открыть сайт",
        "интернет"
      ]
    },
    {
      "name": "play_music",
      "tags": [
        "музыка",
        "плейлист",
        "песня",
        "аудио"
      ]
    },
    {
      "name": "set_volume",
      "tags": [
        "громкость",
        "звук",
        "колонка"
      ]
    },
    {
      "name": "control_light",
      "tags": [
        "свет",
        "лампа",
        "яркость",
        "включить свет"
      ]
    },
    {
      "name": "search_web",
      "tags": [
        "найти",
        "поиск в интернете",
        "интернет"
      ]
    },
    {
      "name": "open_file",
      "tags": [
        "открыть файл",
        "документ",
        "путь к файлу",
        "прочитать файл"
      ]
    },
    {
      "name": "create_note",
      "tags": [
        "заметка",
        "записать",
        "список дел"
      ]
    },
    {
      "name": "send_email",
      "tags": [
        "почта",
        "письмо",
        "сообщение",
        "отправить письмо"
      ]
    },
    {
      "name": "get_weather",
      "tags": [
        "погода",
        "прогноз",
        "температура",
        "дождь"
      ]
    },
    {
      "name": "list_processes",
      "tags": [
        "процессы",
        "задачи",
        "запущенные приложения"
      ]
    },
    {
      "name": "restart_service",
      "tags": [
        "перезапуск",
        "сервис",
        "демон",
        "перезагрузка сервиса"
      ]
    },
    {
      "name": "translate_text",
      "tags": [
        "перевод",
        "язык",
        "перевести",
        "текст"
      ]
    },
    {
      "name": "calculate_math",
      "tags": [
        "математика",
        "посчитать",
        "сумма",
        "число"
      ]
    },
    {
      "name": "take_screenshot",
      "tags": [
        "скриншот",
        "экран",
        "снимок экрана",
        "изображение"
      ]
    },
    {
      "name": "restart_computer",
      "tags": [
        "перезагрузка компьютера",
        "перезапусти mac",
        "reboot"
      ]
    },
    {
      "name": "install_package",
      "tags": [
        "установить пакет",
        "npm install",
        "pip install"
      ]
    },
    {
      "name": "delete_file",
      "tags": [
        "удалить файл",
        "стереть",
        "rm"
      ]
    },
    {
      "name": "edit_config",
      "tags": [
        "изменить конфиг",
        "настройки",
        "правка файла"
      ]
    },
    {
      "name": "run_tests",
      "tags": [
        "тесты",
        "pytest",
        "npm test",
        "запуск тестов"
      ]
    },
    {
      "name": "git_commit",
      "tags": [
        "коммит",
        "закоммить",
        "git commit"
      ]
    },
    {
      "name": "git_push",
      "tags": [
        "push",
        "отправить изменения",
        "git push"
      ]
    }
  ],
  "training_tools": [
    {
      "name": "docker_list_containers",
      "tags": [
        "docker",
        "docker ps",
        "докер",
        "контейнеры",
        "список контейнеров",
        "запущенные контейнеры"
      ],
      "arguments_schema": {
        "type": "object",
        "properties": {
          "state": {
            "type": "string",
            "description": "Какие Docker контейнеры показать.",
            "enum": [
              "running: только запущенные контейнеры, docker ps",
              "all: все контейнеры включая остановленные, docker ps --all"
            ]
          }
        },
        "required": [
          "state"
        ]
      }
    },
    {
      "name": "docker_show_logs",
      "tags": [
        "docker",
        "docker logs",
        "докер",
        "логи контейнера",
        "журнал контейнера",
        "посмотреть логи докера"
      ]
    },
    {
      "name": "docker_restart_container",
      "tags": [
        "docker",
        "docker restart",
        "докер",
        "перезапуск контейнера",
        "рестарт контейнера"
      ]
    },
    {
      "name": "docker_build_image",
      "tags": [
        "docker",
        "docker build",
        "докер",
        "сборка образа",
        "образ докера"
      ]
    },
    {
      "name": "docker_compose_up",
      "tags": [
        "docker compose",
        "compose up",
        "докер компоуз",
        "контейнеры компоуз",
        "запуск компоуза"
      ]
    },
    {
      "name": "docker_stop_container",
      "tags": [
        "docker",
        "docker stop",
        "докер",
        "остановка контейнера",
        "остановить контейнер"
      ]
    },
    {
      "name": "docker_pull_image",
      "tags": [
        "docker",
        "docker pull",
        "докер",
        "загрузка образа",
        "скачать образ"
      ]
    },
    {
      "name": "git_status",
      "tags": [
        "git",
        "git status",
        "гит",
        "статус гита",
        "состояние репозитория",
        "изменения в репозитории"
      ]
    },
    {
      "name": "git_diff",
      "tags": [
        "git",
        "git diff",
        "diff",
        "гит",
        "разница в гите",
        "изменения в коде",
        "разница файлов"
      ]
    },
    {
      "name": "git_log",
      "tags": [
        "git",
        "git log",
        "гит",
        "история коммитов",
        "последние коммиты",
        "лог гита"
      ]
    },
    {
      "name": "git_pull",
      "tags": [
        "git",
        "git pull",
        "гит",
        "обнови репозиторий",
        "получи изменения",
        "подтяни изменения"
      ]
    },
    {
      "name": "git_branch",
      "tags": [
        "git",
        "git branch",
        "гит",
        "ветка гита",
        "текущая ветка",
        "список веток"
      ]
    },
    {
      "name": "git_checkout_branch",
      "tags": [
        "git",
        "git checkout",
        "гит",
        "переключение ветки",
        "смена ветки"
      ]
    },
    {
      "name": "git_stash_changes",
      "tags": [
        "git",
        "git stash",
        "stash",
        "гит",
        "стэш",
        "сохранение изменений",
        "спрятать изменения"
      ]
    },
    {
      "name": "list_home_files",
      "tags": [
        "файлы дома",
        "домашняя папка",
        "список файлов",
        "покажи файлы"
      ]
    },
    {
      "name": "get_ip_address",
      "tags": [
        "ip",
        "айпи адрес",
        "сетевой адрес",
        "адрес сети"
      ]
    },
    {
      "name": "get_memory_usage",
      "tags": [
        "память",
        "использование памяти",
        "оперативная память",
        "сколько памяти"
      ]
    },
    {
      "name": "get_cpu_usage",
      "tags": [
        "cpu",
        "процессор",
        "нагрузка процессора",
        "использование процессора",
        "загрузка процессора"
      ]
    },
    {
      "name": "list_running_processes",
      "tags": [
        "процессы",
        "запущенные процессы",
        "список процессов"
      ]
    },
    {
      "name": "get_os_info",
      "tags": [
        "операционная система",
        "версия системы",
        "информация о системе",
        "система"
      ]
    },
    {
      "name": "read_text_file",
      "tags": [
        "прочитать файл",
        "показать файл",
        "текстовый файл",
        "содержимое файла"
      ],
      "arguments_schema": {
        "type": "object",
        "properties": {
          "path": {
            "type": "string",
            "description": "Относительный путь к безопасному текстовому файлу внутри проекта."
          }
        },
        "required": [
          "path"
        ]
      }
    },
    {
      "name": "search_files",
      "tags": [
        "найти файл",
        "поиск файлов",
        "искать файл",
        "имя файла"
      ],
      "arguments_schema": {
        "type": "object",
        "properties": {
          "query": {
            "type": "string",
            "description": "Имя файла или часть пути для поиска внутри проекта."
          }
        },
        "required": [
          "query"
        ]
      }
    },
    {
      "name": "grep_project",
      "tags": [
        "поиск по коду",
        "grep",
        "найти в коде",
        "строка в проекте"
      ],
      "arguments_schema": {
        "type": "object",
        "properties": {
          "query": {
            "type": "string",
            "description": "Строка или символ, который нужно найти в файлах проекта."
          }
        },
        "required": [
          "query"
        ]
      }
    },
    {
      "name": "inspect_package_json",
      "tags": [
        "package json",
        "скрипты npm",
        "зависимости npm",
        "пакет фронтенда"
      ],
      "arguments_schema": {
        "type": "object",
        "properties": {
          "section": {
            "type": "string",
            "description": "Раздел package.json, который нужно посмотреть.",
            "enum": [
              "scripts: npm scripts из package.json",
              "dependencies: runtime зависимости фронтенда",
              "devDependencies: dev зависимости фронтенда",
              "name: имя npm package"
            ]
          }
        },
        "required": [
          "section"
        ]
      }
    },
    {
      "name": "list_node_packages",
      "tags": [
        "node пакеты",
        "npm зависимости",
        "пакеты фронтенда",
        "зависимости node"
      ],
      "arguments_schema": {
        "type": "object",
        "properties": {
          "scope": {
            "type": "string",
            "description": "Какие npm зависимости вывести.",
            "enum": [
              "all: dependencies и devDependencies вместе",
              "dependencies: только runtime dependencies",
              "devDependencies: только devDependencies"
            ]
          }
        },
        "required": [
          "scope"
        ]
      }
    },
    {
      "name": "list_python_packages",
      "tags": [
        "python пакеты",
        "pip пакеты",
        "зависимости python",
        "requirements"
      ],
      "arguments_schema": {
        "type": "object",
        "properties": {
          "filter": {
            "type": "string",
            "description": "Фильтр по имени python пакета или пустая строка для всех пакетов."
          }
        },
        "required": [
          "filter"
        ]
      }
    },
    {
      "name": "check_http_head",
      "tags": [
        "проверить url",
        "http head",
        "доступность сайта",
        "подключение к сайту"
      ],
      "arguments_schema": {
        "type": "object",
        "properties": {
          "target": {
            "type": "string",
            "description": "Какой разрешённый endpoint проверить.",
            "enum": [
              "example_com: https://example.com для базовой проверки интернета",
              "pypi: https://pypi.org для проверки Python package index",
              "npm_registry: https://registry.npmjs.org для проверки npm registry",
              "github: https://github.com для проверки доступности GitHub"
            ]
          }
        },
        "required": [
          "target"
        ]
      }
    },
    {
      "name": "list_directory",
      "tags": [
        "папка загрузок",
        "загрузки",
        "скачанные файлы",
        "список файлов",
        "файлы проекта",
        "корень проекта",
        "папка проекта",
        "директория"
      ],
      "arguments_schema": {
        "type": "object",
        "properties": {
          "directory": {
            "type": "string",
            "description": "Какую разрешённую директорию показать.",
            "enum": [
              "downloads: папка загрузок текущего пользователя",
              "project_root: корень текущего проекта Proton AI",
              "service: FastAPI сервис модели в папке service",
              "web_backend: FastAPI backend для UI",
              "web_ui: React/Vite интерфейс оператора",
              "data: локальные данные, датасеты и артефакты проекта"
            ]
          }
        },
        "required": [
          "directory"
        ]
      }
    },
    {
      "name": "get_node_version",
      "tags": [
        "node",
        "node js",
        "node version",
        "npm",
        "npm version",
        "npm -v",
        "версия ноды",
        "версия node js",
        "версия npm",
        "нода",
        "нпм",
        "какая нода"
      ],
      "arguments_schema": {
        "type": "object",
        "properties": {
          "target": {
            "type": "string",
            "description": "Версию какого инструмента показать.",
            "enum": [
              "node: версия Node.js через node --version",
              "npm: версия npm через npm --version"
            ]
          }
        },
        "required": [
          "target"
        ]
      }
    }
  ],
  "templates": {
    "ru": [
      "{phrase}",
      "покажи {phrase}",
      "проверь {phrase}",
      "выведи {phrase}",
      "отобрази {phrase}",
      "можешь проверить {phrase}",
      "хочу увидеть {phrase}",
      "покажи мне {phrase}",
      "можешь показать {phrase}",
      "подскажи {phrase}",
      "посмотри {phrase}",
      "проверь пожалуйста {phrase}",
      "выведи пожалуйста {phrase}",
      "надо {phrase}",
      "нужно {phrase}",
      "сделай {phrase}",
      "дай {phrase}",
      "выведи мне {phrase}",
      "покажи пожалуйста {phrase}",
      "можешь вывести {phrase}",
      "нужно проверить {phrase}",
      "надо посмотреть {phrase}",
      "для диагностики покажи {phrase}",
      "на локальной машине покажи {phrase}",
      "в этом проекте покажи {phrase}",
      "а можешь {phrase}",
      "а ну {phrase}",
      "сможешь {phrase}",
      "плиз {phrase}",
      "мне надо {phrase}",
      "проверь-ка {phrase}"
    ]
  },
  "ru_request_wrappers": [
    "{request}",
    "{request} пожалуйста",
    "мне нужно: {request}",
    "сейчас {request}",
    "быстро {request}",
    "можешь выполнить: {request}",
    "для проверки {request}",
    "на этом компьютере {request}",
    "в системе {request}",
    "локально {request}",
    "пожалуйста, {request}",
    "а теперь {request}",
    "можешь {request}",
    "надо {request}",
    "нужно {request}",
    "пожалуйста сделай: {request}",
    "если можно, {request}",
    "хочу чтобы ты {request}",
    "дай мне результат: {request}",
    "просто {request}",
    "для диагностики: {request}",
    "на локальной машине: {request}",
    "в текущем проекте: {request}",
    "мне нужен вывод: {request}",
    "без лишнего текста {request}",
    "проверь и покажи: {request}",
    "посмотри сейчас: {request}",
    "сделай readonly проверку: {request}",
    "Пожалуйста, {request}",
    "Сейчас надо: {request}",
    "МОЖЕШЬ {request}",
    "плз {request}",
    "ок, {request}",
    "алло, {request}"
  ],
  "tools": {
    "get_node_version": {
      "ru": [
        "версия ноды",
        "версия node",
        "версия npm",
        "нода",
        "npm",
        "нпм",
        "node -v",
        "npm -v",
        "nodejs version",
        "npm version",
        "релиз node",
        "релиз npm",
        "пакетный менеджер npm",
        "версия пакетного менеджера"
      ],
      "requests": [
        "покажи версию ноды",
        "какая версия ноды у меня установлена",
        "узнай версию ноды",
        "проверь ноду",
        "покажи node -v",
        "покажи npm -v",
        "какая версия npm установлена",
        "узнай версию npm",
        "сообщи версию node",
        "сообщи версию npm",
        "какой nodejs стоит",
        "какой npm стоит",
        "проверь node --version",
        "проверь npm --version",
        "выведи node --version",
        "выведи npm --version",
        "хочу узнать релиз ноды",
        "хочу узнать релиз npm",
        "какой пакетный менеджер npm установлен",
        "проверь версию пакетного менеджера"
      ]
    },
    "get_python_version": {
      "ru": [
        "версия питона",
        "питон",
        "интерпретатор",
        "какой питон",
        "python --version",
        "python3 version",
        "релиз python",
        "активный python"
      ],
      "requests": [
        "какая версия питона у меня установлена",
        "покажи версию питона",
        "узнай версию питона",
        "проверь питон",
        "какой питон установлен",
        "покажи интерпретатор питона",
        "сообщи версию python",
        "какой python сейчас активен",
        "проверь python --version",
        "выведи версию python3",
        "узнай релиз интерпретатора python"
      ]
    },
    "get_current_time": {
      "ru": [
        "время",
        "текущее время",
        "дата",
        "который час",
        "сколько времени",
        "локальное время",
        "системное время",
        "текущая дата",
        "дата и время"
      ],
      "requests": [
        "который час",
        "сколько времени",
        "покажи текущее время",
        "какая сейчас дата",
        "скажи дату и время",
        "узнай время на компьютере",
        "сообщи системное время",
        "какая дата на компьютере",
        "выведи локальное время",
        "проверь часы системы",
        "покажи дату и время сейчас"
      ]
    },
    "get_disk_usage": {
      "ru": [
        "диск",
        "место на диске",
        "свободное место",
        "размер диска",
        "сколько места",
        "disk usage",
        "df",
        "свободное место home",
        "занято на диске"
      ],
      "requests": [
        "размер диска",
        "проверь место на диске",
        "покажи свободное место",
        "сколько свободного места на диске",
        "узнай состояние диска",
        "сообщи сколько места осталось",
        "покажи занятое место на домашнем разделе",
        "проверь свободное место home",
        "выведи disk usage",
        "сколько осталось памяти на диске"
      ]
    },
    "docker_list_containers": {
      "ru": [
        "контейнеры докера",
        "список контейнеров",
        "запущенные контейнеры",
        "контейнеры",
        "docker ps",
        "docker ps -a",
        "docker ps all",
        "все docker контейнеры",
        "остановленные контейнеры",
        "running containers",
        "активные контейнеры"
      ],
      "requests": [
        "покажи контейнеры докера",
        "какие контейнеры запущены",
        "выведи список контейнеров",
        "список контейнеров докера",
        "покажи docker ps",
        "покажи все контейнеры docker",
        "покажи только работающие контейнеры",
        "какие docker контейнеры сейчас running",
        "выведи активные контейнеры докера",
        "посмотри запущенные контейнеры",
        "покажи docker ps --all",
        "покажи контейнеры включая остановленные",
        "какие контейнеры есть вообще",
        "покажи stopped контейнеры тоже"
      ]
    },
    "docker_show_logs": {
      "ru": [
        "логи докера",
        "логи контейнера",
        "журнал контейнера"
      ],
      "requests": [
        "покажи логи контейнера",
        "выведи логи докера",
        "посмотри журнал контейнера",
        "нужны логи докера"
      ]
    },
    "docker_restart_container": {
      "ru": [
        "перезапуск контейнера",
        "рестарт контейнера",
        "рестарт докера"
      ],
      "requests": [
        "перезапусти контейнер докера",
        "сделай рестарт контейнера",
        "нужно перезапустить контейнер",
        "рестартани контейнер"
      ]
    },
    "docker_build_image": {
      "ru": [
        "сборка образа докера",
        "образ докера",
        "сборка образа"
      ],
      "requests": [
        "собери образ докера",
        "запусти сборку образа",
        "нужно собрать образ докера",
        "построй образ контейнера"
      ]
    },
    "docker_compose_up": {
      "ru": [
        "докер компоуз",
        "контейнеры компоуз",
        "запуск компоуза"
      ],
      "requests": [
        "подними докер компоуз",
        "запусти компоуз",
        "нужно поднять контейнеры компоуз",
        "стартуй докер компоуз"
      ]
    },
    "docker_stop_container": {
      "ru": [
        "остановка контейнера",
        "остановить контейнер"
      ],
      "requests": [
        "останови контейнер докера",
        "сделай остановку контейнера",
        "нужно остановить контейнер",
        "останови докер контейнер"
      ]
    },
    "docker_pull_image": {
      "ru": [
        "загрузка образа докера",
        "скачать образ",
        "получить образ"
      ],
      "requests": [
        "скачай образ докера",
        "загрузи образ докера",
        "нужно загрузить образ докера",
        "получи образ контейнера"
      ]
    },
    "git_status": {
      "ru": [
        "статус гита",
        "состояние репозитория",
        "изменения в репозитории"
      ],
      "requests": [
        "покажи статус гита",
        "какой статус репозитория",
        "выведи статус гита",
        "проверь изменения в репозитории"
      ]
    },
    "git_diff": {
      "ru": [
        "разница в гите",
        "изменения в коде",
        "разница файлов"
      ],
      "requests": [
        "покажи разницу в гите",
        "какие изменения в коде",
        "выведи разницу",
        "посмотри разницу файлов"
      ]
    },
    "git_log": {
      "ru": [
        "лог гита",
        "история коммитов",
        "последние коммиты"
      ],
      "requests": [
        "покажи лог гита",
        "покажи последние коммиты",
        "какая история коммитов",
        "выведи лог гита"
      ]
    },
    "git_pull": {
      "ru": [
        "обнови репозиторий",
        "подтяни изменения",
        "получи изменения"
      ],
      "requests": [
        "обнови репозиторий через гит",
        "обнови репозиторий",
        "подтяни изменения из гита",
        "получи последние изменения"
      ]
    },
    "git_branch": {
      "ru": [
        "ветка гита",
        "текущая ветка",
        "список веток"
      ],
      "requests": [
        "покажи ветку гита",
        "какая текущая ветка",
        "выведи ветки гита",
        "список веток гита"
      ]
    },
    "git_checkout_branch": {
      "ru": [
        "переключение ветки",
        "смена ветки"
      ],
      "requests": [
        "переключи ветку гита",
        "сделай переключение ветки",
        "нужно сменить ветку",
        "перейди на другую ветку"
      ]
    },
    "git_stash_changes": {
      "ru": [
        "стэш гита",
        "сохранение изменений",
        "спрятать изменения"
      ],
      "requests": [
        "сделай стэш гита",
        "спрячь текущие изменения",
        "сохрани изменения в стэш",
        "убери изменения во временное хранилище"
      ]
    },
    "list_home_files": {
      "ru": [
        "домашняя папка",
        "файлы дома",
        "список файлов",
        "что в домашней папке"
      ],
      "requests": [
        "покажи файлы в домашней папке",
        "что лежит дома",
        "список файлов дома",
        "выведи домашнюю папку"
      ]
    },
    "get_ip_address": {
      "ru": [
        "айпи адрес",
        "сетевой адрес",
        "адрес сети",
        "мой айпи"
      ],
      "requests": [
        "покажи айпи адрес",
        "какой сетевой адрес",
        "узнай мой айпи",
        "выведи айпи"
      ]
    },
    "get_memory_usage": {
      "ru": [
        "память",
        "оперативная память",
        "использование памяти",
        "сколько памяти"
      ],
      "requests": [
        "покажи использование памяти",
        "сколько оперативной памяти занято",
        "проверь память",
        "выведи состояние памяти"
      ]
    },
    "get_cpu_usage": {
      "ru": [
        "процессор",
        "нагрузка процессора",
        "загрузка процессора"
      ],
      "requests": [
        "покажи нагрузку процессора",
        "сколько загружен процессор",
        "проверь процессор",
        "выведи загрузку процессора"
      ]
    },
    "list_running_processes": {
      "ru": [
        "процессы",
        "запущенные процессы",
        "список процессов",
        "активные процессы"
      ],
      "requests": [
        "покажи запущенные процессы",
        "выведи список процессов",
        "какие процессы сейчас работают",
        "проверь активные процессы"
      ]
    },
    "get_os_info": {
      "ru": [
        "операционная система",
        "версия системы",
        "информация о системе",
        "какая система"
      ],
      "requests": [
        "покажи информацию о системе",
        "какая операционная система",
        "узнай версию системы",
        "выведи сведения о системе"
      ]
    },
    "read_text_file": {
      "ru": [
        "прочитать файл",
        "содержимое файла",
        "показать файл",
        "текстовый файл"
      ],
      "requests": [
        "прочитай файл проекта",
        "покажи содержимое файла",
        "открой текстовый файл для чтения",
        "выведи файл без изменений"
      ]
    },
    "search_files": {
      "ru": [
        "найти файл",
        "поиск файлов",
        "искать файл",
        "имя файла"
      ],
      "requests": [
        "найди файл в проекте",
        "поищи файл по имени",
        "найди где лежит файл",
        "поиск файла в проекте"
      ]
    },
    "grep_project": {
      "ru": [
        "поиск по коду",
        "найти в коде",
        "grep",
        "строка в проекте"
      ],
      "requests": [
        "найди строку в проекте",
        "поищи по коду",
        "где используется символ",
        "сделай поиск по файлам проекта"
      ]
    },
    "inspect_package_json": {
      "ru": [
        "package json",
        "скрипты npm",
        "зависимости npm",
        "пакет фронтенда"
      ],
      "requests": [
        "покажи package json",
        "посмотри скрипты npm",
        "какие зависимости в package json",
        "проверь package json фронтенда"
      ]
    },
    "list_node_packages": {
      "ru": [
        "node пакеты",
        "npm зависимости",
        "пакеты фронтенда",
        "зависимости node"
      ],
      "requests": [
        "покажи node пакеты",
        "выведи npm зависимости",
        "какие пакеты у фронтенда",
        "посмотри зависимости node"
      ]
    },
    "list_python_packages": {
      "ru": [
        "python пакеты",
        "pip пакеты",
        "зависимости python",
        "requirements"
      ],
      "requests": [
        "покажи python пакеты",
        "выведи pip пакеты",
        "посмотри зависимости python",
        "какие пакеты установлены для сервиса"
      ]
    },
    "check_http_head": {
      "ru": [
        "проверить интернет",
        "http head",
        "curl head",
        "доступность сайта",
        "подключение к сайту",
        "head github",
        "head pypi",
        "head npm registry",
        "проверка github",
        "проверка pypi",
        "проверка registry npm",
        "доступность endpoint"
      ],
      "requests": [
        "проверь подключение к интернету",
        "сделай curl head к example.com",
        "проверь доступность pypi",
        "проверь github через head запрос",
        "узнай доступен ли npm registry",
        "проверь github.com head запросом",
        "доступен ли github.com",
        "проверь pypi.org head запросом",
        "доступен ли python registry",
        "проверь registry.npmjs.org",
        "доступен ли npm реестр",
        "сделай безопасную head проверку npm registry",
        "сделай head проверку github",
        "сделай head проверку pypi",
        "проверь example.com для интернета"
      ]
    },
    "list_directory": {
      "ru": [
        "загрузки",
        "папка загрузок",
        "файлы проекта",
        "корень проекта",
        "папка сервиса",
        "папка фронтенда",
        "директория",
        "что в папке",
        "содержимое директории",
        "листинг папки",
        "корень репозитория",
        "папка backend",
        "папка ui",
        "папка данных",
        "папка downloads"
      ],
      "requests": [
        "покажи папку загрузок",
        "покажи файлы в корне проекта",
        "выведи список файлов проекта",
        "что лежит в service",
        "покажи папку web_ui",
        "покажи папку data",
        "покажи содержимое загрузок",
        "покажи что скачано",
        "отобрази downloads",
        "покажи верхний уровень проекта",
        "выведи корневую директорию проекта",
        "что лежит в backend",
        "что внутри web backend",
        "покажи backend папку",
        "что внутри web ui",
        "покажи frontend папку",
        "покажи данные проекта",
        "посмотри папку с датасетами",
        "выведи список локальных данных"
      ]
    }
  },
  "argument_examples": {
    "read_text_file": [
      {
        "arguments": {
          "path": "README.md"
        },
        "requests": [
          "прочитай README.md",
          "покажи README проекта",
          "выведи файл README.md"
        ]
      },
      {
        "arguments": {
          "path": "service/README.md"
        },
        "requests": [
          "прочитай service README",
          "покажи документацию сервиса",
          "выведи service/README.md"
        ]
      },
      {
        "arguments": {
          "path": "web_ui/package.json"
        },
        "requests": [
          "покажи package json фронтенда",
          "прочитай web_ui/package.json",
          "выведи package.json ui"
        ]
      }
    ],
    "search_files": [
      {
        "arguments": {
          "query": "package.json"
        },
        "requests": [
          "найди package.json",
          "где лежит package json",
          "поищи файл package.json"
        ]
      },
      {
        "arguments": {
          "query": "Dockerfile"
        },
        "requests": [
          "найди Dockerfile",
          "есть ли Dockerfile в проекте",
          "поищи докерфайл"
        ]
      },
      {
        "arguments": {
          "query": "requirements.txt"
        },
        "requests": [
          "найди requirements.txt",
          "где requirements сервиса",
          "поищи файл requirements"
        ]
      }
    ],
    "grep_project": [
      {
        "arguments": {
          "query": "build_examples"
        },
        "requests": [
          "найди где используется build_examples",
          "поищи build_examples в коде",
          "где функция build_examples"
        ]
      },
      {
        "arguments": {
          "query": "fallback_ratio"
        },
        "requests": [
          "найди fallback_ratio в проекте",
          "где задается процент fallback",
          "поищи fallback ratio"
        ]
      },
      {
        "arguments": {
          "query": "fallback_ratio"
        },
        "requests": [
          "найди fallback_ratio",
          "где задается процент fallback",
          "поищи fallback ratio"
        ]
      }
    ],
    "inspect_package_json": [
      {
        "arguments": {
          "section": "scripts"
        },
        "requests": [
          "покажи scripts в package.json",
          "какие npm scripts есть",
          "выведи скрипты фронтенда"
        ]
      },
      {
        "arguments": {
          "section": "dependencies"
        },
        "requests": [
          "покажи dependencies package json",
          "какие runtime зависимости фронтенда",
          "выведи зависимости npm"
        ]
      },
      {
        "arguments": {
          "section": "devDependencies"
        },
        "requests": [
          "покажи devDependencies",
          "какие dev зависимости у ui",
          "выведи dev пакеты npm"
        ]
      }
    ],
    "list_node_packages": [
      {
        "arguments": {
          "scope": "all"
        },
        "requests": [
          "покажи все node зависимости",
          "выведи все npm пакеты",
          "какие node packages есть"
        ]
      },
      {
        "arguments": {
          "scope": "dependencies"
        },
        "requests": [
          "покажи обычные npm dependencies",
          "выведи runtime node зависимости",
          "какие dependencies в ui"
        ]
      },
      {
        "arguments": {
          "scope": "devDependencies"
        },
        "requests": [
          "покажи dev npm dependencies",
          "выведи devDependencies node",
          "какие dev пакеты фронтенда"
        ]
      }
    ],
    "list_python_packages": [
      {
        "arguments": {
          "filter": ""
        },
        "requests": [
          "покажи python packages",
          "выведи все pip пакеты",
          "какие python зависимости доступны"
        ]
      },
      {
        "arguments": {
          "filter": "fastapi"
        },
        "requests": [
          "найди пакет fastapi",
          "проверь установлен ли fastapi",
          "покажи pip пакет fastapi"
        ]
      },
      {
        "arguments": {
          "filter": "torch"
        },
        "requests": [
          "найди пакет torch",
          "проверь установлен ли torch",
          "покажи pip пакет torch"
        ]
      }
    ],
    "check_http_head": [
      {
        "arguments": {
          "target": "example_com"
        },
        "requests": [
          "проверь https://example.com",
          "сделай head запрос к example.com",
          "доступен ли example.com",
          "проверь example.com head",
          "доступен ли example.com сейчас",
          "head запрос к example com",
          "базовая проверка интернета через example",
          "сделай readonly проверку example.com",
          "проверь соединение на example.com",
          "example.com отвечает или нет",
          "Example.com проверь head",
          "EXAMPLE.COM проверка",
          "example доступен?",
          "проверь Example dot com",
          "head Example без скачивания"
        ]
      },
      {
        "arguments": {
          "target": "pypi"
        },
        "requests": [
          "проверь доступность pypi",
          "сделай head запрос к pypi.org",
          "доступен ли pypi.org",
          "проверь python package index",
          "доступен ли pypi сейчас",
          "head запрос к pypi",
          "проверь pypi.org без скачивания",
          "сделай readonly проверку pypi.org",
          "python registry отвечает или нет",
          "проверь доступ до pypi",
          "PyPI проверь head",
          "PYPI.ORG проверка",
          "pypi доступен?",
          "проверь Python registry",
          "head PyPI без скачивания"
        ]
      },
      {
        "arguments": {
          "target": "npm_registry"
        },
        "requests": [
          "проверь npm registry",
          "сделай head запрос к npm registry",
          "доступен ли registry.npmjs.org",
          "проверь npm registry head",
          "доступен ли registry npmjs",
          "head запрос к npm реестру",
          "проверь npm registry без скачивания",
          "сделай readonly проверку registry.npmjs.org",
          "npm реестр отвечает или нет",
          "проверь доступ до npm registry",
          "NPM registry проверь head",
          "REGISTRY.NPMJS.ORG проверка",
          "npm Registry доступен?",
          "проверь npm Registry",
          "head NPM registry без скачивания"
        ]
      },
      {
        "arguments": {
          "target": "github"
        },
        "requests": [
          "проверь github",
          "сделай head запрос к github.com",
          "доступен ли github",
          "проверь github head",
          "доступен ли github сейчас",
          "head запрос к github",
          "проверь github.com без скачивания",
          "сделай readonly проверку github.com",
          "github отвечает или нет",
          "проверь доступ до github",
          "GitHub проверь head",
          "GITHUB HEAD проверка",
          "github доступен?",
          "проверь GitHub.com",
          "head GitHub без скачивания"
        ]
      }
    ],
    "get_node_version": [
      {
        "arguments": {
          "target": "node"
        },
        "requests": [
          "покажи node -v",
          "какая версия node установлена",
          "проверь версию ноды",
          "узнай node version",
          "версия ноды",
          "какая нода",
          "покажи версию node",
          "сообщи релиз node runtime",
          "какая версия nodejs runtime",
          "покажи node --version",
          "нужно узнать node version",
          "проверь установленный node",
          "выведи версию nodejs",
          "какой node runtime доступен",
          "покажи версию ноды на машине",
          "узнай текущую ноду",
          "node version локально",
          "проверка node -v",
          "какой релиз ноды стоит",
          "Node покажи версию",
          "NODE VERSION покажи",
          "node Version локально",
          "покажи Node runtime",
          "выведи NODE --version",
          "какая Node версия"
        ]
      },
      {
        "arguments": {
          "target": "npm"
        },
        "requests": [
          "покажи npm -v",
          "какая версия npm установлена",
          "проверь версию npm",
          "узнай npm version",
          "версия npm",
          "какой npm",
          "покажи версию npm",
          "сообщи релиз npm cli",
          "какая версия npm cli",
          "покажи npm --version",
          "нужно узнать npm version",
          "проверь установленный npm",
          "выведи версию npm cli",
          "какой npm доступен",
          "покажи версию пакетного менеджера npm",
          "узнай текущий npm",
          "npm version локально",
          "проверка npm -v",
          "какой релиз npm стоит",
          "NPM покажи версию",
          "NPM VERSION покажи",
          "npm Version локально",
          "покажи NPM cli",
          "выведи NPM --version",
          "какая Npm версия"
        ]
      }
    ],
    "list_directory": [
      {
        "arguments": {
          "directory": "downloads"
        },
        "requests": [
          "покажи папку загрузок",
          "что лежит в загрузках",
          "выведи скачанные файлы",
          "покажи содержимое downloads",
          "что сейчас в downloads",
          "выведи список скачанных файлов",
          "посмотри папку загрузок пользователя",
          "проверь downloads директорию",
          "листинг папки загрузки",
          "что лежит в папке скачанного",
          "покажи мои загрузки",
          "покажи Downloads",
          "листинг Downloads",
          "что в Downloads",
          "выведи Downloads директорию"
        ]
      },
      {
        "arguments": {
          "directory": "project_root"
        },
        "requests": [
          "покажи файлы в корне проекта",
          "что лежит в корне репозитория",
          "выведи project root",
          "покажи верхний уровень репозитория",
          "что в корне proton ai",
          "выведи корень проекта",
          "посмотри project root",
          "листинг корневой папки проекта",
          "что лежит рядом с README",
          "покажи файлы верхнего уровня",
          "проверь корневую директорию",
          "покажи PROJECT ROOT",
          "листинг PROJECT ROOT",
          "что в PROJECT ROOT",
          "выведи PROJECT ROOT директорию"
        ]
      },
      {
        "arguments": {
          "directory": "service"
        },
        "requests": [
          "покажи файлы service",
          "что лежит в service",
          "выведи папку сервиса",
          "покажи директорию service",
          "что внутри model service",
          "выведи файлы сервиса",
          "посмотри папку fastapi сервиса",
          "листинг service директории",
          "что лежит в backend модели",
          "проверь папку service",
          "покажи содержимое service",
          "покажи Service",
          "листинг Service",
          "что в Service",
          "выведи Service директорию"
        ]
      },
      {
        "arguments": {
          "directory": "web_backend"
        },
        "requests": [
          "покажи файлы web_backend",
          "что лежит в backend ui",
          "выведи папку web backend",
          "покажи директорию web_backend",
          "что внутри ui backend",
          "выведи файлы web backend",
          "посмотри bff backend",
          "листинг web_backend директории",
          "проверь папку web backend",
          "покажи backend для интерфейса",
          "что лежит в web_backend",
          "покажи WEB BACKEND",
          "листинг WEB BACKEND",
          "что в WEB BACKEND",
          "выведи WEB BACKEND директорию"
        ]
      },
      {
        "arguments": {
          "directory": "web_ui"
        },
        "requests": [
          "покажи файлы web_ui",
          "что лежит во фронтенде",
          "выведи папку ui",
          "покажи директорию web_ui",
          "что внутри react интерфейса",
          "выведи файлы frontend",
          "посмотри vite ui",
          "листинг web_ui директории",
          "проверь папку web ui",
          "покажи фронтенд проекта",
          "что лежит в web_ui",
          "покажи WEB UI",
          "листинг WEB UI",
          "что в WEB UI",
          "выведи WEB UI директорию"
        ]
      },
      {
        "arguments": {
          "directory": "data"
        },
        "requests": [
          "покажи папку data",
          "что лежит в data",
          "выведи локальные данные проекта",
          "покажи директорию data",
          "что внутри локальных данных",
          "выведи файлы датасетов",
          "посмотри папку с весами и логами",
          "листинг data директории",
          "проверь папку data",
          "покажи данные обучения",
          "что лежит в data проекта",
          "покажи DATA",
          "листинг DATA",
          "что в DATA",
          "выведи DATA директорию"
        ]
      }
    ],
    "docker_list_containers": [
      {
        "arguments": {
          "state": "running"
        },
        "requests": [
          "какие контейнеры запущены",
          "выведи запущенные docker контейнеры",
          "покажи docker ps",
          "покажи только running контейнеры",
          "какие контейнеры сейчас работают",
          "выведи docker ps без all",
          "посмотри активные docker контейнеры",
          "нужен список запущенных контейнеров",
          "проверь работающие контейнеры докера",
          "docker ps без остановленных",
          "покажи контейнеры в статусе up",
          "выведи живые контейнеры",
          "какие контейнеры подняты сейчас",
          "Docker PS покажи",
          "DOCKER PS без all",
          "покажи Docker running",
          "контейнеры Docker которые UP",
          "docker ps сейчас локально"
        ]
      },
      {
        "arguments": {
          "state": "all"
        },
        "requests": [
          "покажи все контейнеры docker",
          "выведи все docker контейнеры включая остановленные",
          "покажи docker ps -a",
          "покажи контейнеры вместе с остановленными",
          "выведи docker ps --all",
          "нужен полный список docker контейнеров",
          "посмотри все контейнеры докера",
          "docker ps с флагом all",
          "покажи остановленные контейнеры тоже",
          "какие контейнеры существуют вообще",
          "выведи docker ps -a полностью",
          "покажи все созданные контейнеры",
          "список контейнеров включая exited",
          "Docker PS -A покажи",
          "DOCKER PS --ALL",
          "покажи Docker all containers",
          "контейнеры Docker включая EXITED",
          "docker ps -a сейчас локально"
        ]
      }
    ]
  },
  "unavailable_intents": [
    {
      "family": "git",
      "tool_names": [
        "git_status",
        "git_diff",
        "git_log",
        "git_pull",
        "git_branch",
        "git_checkout_branch",
        "git_stash_changes"
      ],
      "requests": [
        "покажи статус гита",
        "проверь статус гита",
        "выведи разницу в гите",
        "покажи последние коммиты",
        "обнови репозиторий через гит",
        "покажи текущую ветку",
        "переключи ветку гита",
        "сделай стэш гита",
        "что изменилось в репозитории",
        "какая история коммитов",
        "подтяни изменения из гита",
        "спрячь текущие изменения"
      ]
    },
    {
      "family": "docker",
      "tool_names": [
        "docker_list_containers",
        "docker_show_logs",
        "docker_restart_container",
        "docker_build_image",
        "docker_compose_up",
        "docker_stop_container",
        "docker_pull_image"
      ],
      "requests": [
        "покажи контейнеры докера",
        "какие контейнеры запущены",
        "выведи список контейнеров",
        "покажи логи контейнера",
        "перезапусти контейнер докера",
        "собери образ докера",
        "подними докер компоуз",
        "останови контейнер докера",
        "скачай образ докера",
        "посмотри логи докера",
        "нужно поднять контейнеры компоуз",
        "загрузи образ докера"
      ]
    },
    {
      "family": "system_metrics",
      "tool_names": [
        "get_ip_address",
        "get_memory_usage",
        "get_cpu_usage",
        "list_running_processes",
        "get_os_info",
        "get_disk_usage",
        "get_current_time"
      ],
      "requests": [
        "покажи айпи адрес",
        "проверь память",
        "сколько загружен процессор",
        "какие процессы сейчас работают",
        "какая операционная система",
        "проверь место на диске",
        "который час",
        "какая сейчас дата"
      ]
    }
  ],
  "fallback": {
    "ru": [
      "покажи версию",
      "какая версия",
      "какая версия установлена",
      "какая версия у меня установлена",
      "что установлено",
      "покажи установленную версию",
      "покажи статус",
      "проверь состояние",
      "что происходит",
      "сделай это",
      "запусти",
      "выполни команду",
      "почини проект",
      "собери проект",
      "обнови зависимости",
      "запусти тесты",
      "перезапусти приложение",
      "открой терминал",
      "создай файл",
      "удали файл",
      "переименуй папку",
      "найди ошибку",
      "покажи настройки",
      "расскажи что умеешь",
      "помоги мне",
      "объясни код",
      "напиши функцию",
      "сделай рефакторинг",
      "проверь качество",
      "сохрани результат",
      "покажи историю",
      "расскажи шутку",
      "напиши стих",
      "найди в интернете",
      "открой браузер",
      "включи свет",
      "сделай музыку тише",
      "как дела",
      "привет",
      "поболтай со мной",
      "сделай потише",
      "открой",
      "измени это",
      "белеберда",
      "абракадабра",
      "ываываыва",
      "лрлрлр тест",
      "что-нибудь сделай",
      "ну ты понял",
      "сам разберись",
      "покажи вот это",
      "сделай красиво",
      "исправь всё",
      "улучши проект",
      "добавь фичу",
      "сделай норм",
      "просто запусти это",
      "выполни опасную команду",
      "удали все логи",
      "очисти домашнюю папку",
      "сотри проект",
      "перезапиши файл",
      "установи пакет",
      "обнови npm пакеты",
      "сделай npm install",
      "запусти docker build",
      "останови все контейнеры",
      "перезапусти docker",
      "сделай git push",
      "закоммить изменения",
      "сделай git reset",
      "переключись на ветку",
      "создай новую ветку",
      "скачай файл из интернета",
      "отправь запрос в апи",
      "открой сайт",
      "найди новости",
      "покажи погоду",
      "переведи текст",
      "посчитай два плюс два",
      "напиши письмо",
      "создай заметку",
      "включи музыку",
      "поставь будильник",
      "запланируй встречу",
      "напомни завтра",
      "расскажи анекдот",
      "напиши рассказ",
      "объясни квантовую физику",
      "сделай презентацию",
      "нарисуй картинку",
      "создай таблицу",
      "сравни варианты",
      "дай совет",
      "что мне делать",
      "почему не работает",
      "исправь ошибку",
      "найди баг",
      "проведи ревью",
      "напиши тесты",
      "запусти линтер",
      "собери фронтенд",
      "подними сервер",
      "проверь деплой",
      "покажи секреты",
      "выведи токены",
      "прочитай приватный ключ",
      "покажи пароли",
      "зайди в аккаунт",
      "отправь сообщение",
      "позвони контакту",
      "оплати счет",
      "купи подписку",
      "забронируй билет",
      "скажи что-нибудь",
      "поговори со мной",
      "ты кто такой",
      "что ты умеешь",
      "помоги с задачей",
      "сделай по памяти",
      "догадайся сам",
      "выполни без инструмента",
      "выбери любой тул",
      "неважно что вызвать",
      "проверь это",
      "посмотри туда",
      "сделай команду",
      "вызови команду",
      "дай результат",
      "выведи информацию",
      "покажи данные",
      "проверь подключение",
      "открой файл по пути",
      "найди нужный файл",
      "прочитай что-нибудь",
      "покажи нужную папку",
      "запусти нужный скрипт",
      "проверь нужный сервис",
      "сделай curl куда-нибудь",
      "выполни docker команду",
      "проверь npm",
      "покажи версию программы",
      "узнай статус процесса",
      "посмотри состояние системы",
      "покажи что сломалось",
      "найди причину ошибки",
      "пофикси всё автоматически",
      "примени изменения",
      "скажи ответ",
      "asdf qwer zxcv",
      "йцукен фывапр",
      "12345 тест",
      "???",
      "...",
      "проверь непонятно что",
      "сделай какую-нибудь проверку",
      "покажи любую информацию",
      "вызови подходящий инструмент сам",
      "сам выбери команду",
      "можешь что-то выполнить",
      "надо что-то проверить",
      "сделай диагностику",
      "запусти диагностику проекта",
      "посмотри ошибки в проекте",
      "исправь все ошибки автоматически",
      "почини тесты",
      "перепиши код",
      "отформатируй проект",
      "запусти npm run build",
      "запусти pytest",
      "покажи git status",
      "покажи git diff",
      "сделай git pull",
      "сделай git checkout",
      "сделай docker compose up",
      "сделай docker ps без docker tool",
      "перезапусти контейнер",
      "покажи логи контейнера",
      "скачай docker образ",
      "собери docker image",
      "проверь неизвестный сайт",
      "сделай curl на мой url",
      "проверь https://openai.com",
      "проверь localhost",
      "проверь api endpoint",
      "отправь post запрос",
      "прочитай произвольный файл",
      "покажи файл с секретами",
      "открой ssh ключ",
      "покажи .env",
      "выведи переменные окружения",
      "покажи историю терминала",
      "проверь процесс python",
      "убей процесс",
      "останови сервер",
      "перезапусти backend",
      "очисти кеш",
      "удали node_modules",
      "установи зависимости",
      "обнови pip пакеты",
      "зайди в браузер и найди",
      "найди документацию в интернете",
      "ответь без инструментов",
      "объясни почему ошибка",
      "придумай архитектуру",
      "составь план работ",
      "сделай ревью кода",
      "напиши миграцию",
      "создай pull request",
      "запушь ветку",
      "смерджи изменения",
      "переведи это на английский",
      "сгенерируй картинку",
      "сделай презентацию по проекту",
      "посчитай бюджет",
      "заполни таблицу",
      "отправь письмо заказчику",
      "включи тёмную тему",
      "измени настройки системы",
      "открой приложение",
      "%%%%",
      "фыва олдж",
      "qweqweqwe",
      "каша из слов без смысла"
    ]
  }
}
